odoo/addons/stock_orderpoint_purchase_link/README.rst
odoo/addons/stock_orderpoint_purchase_link/__init__.py
odoo/addons/stock_orderpoint_purchase_link/__manifest__.py
odoo/addons/stock_orderpoint_purchase_link/i18n/stock_orderpoint_purchase_link.pot
odoo/addons/stock_orderpoint_purchase_link/models/__init__.py
odoo/addons/stock_orderpoint_purchase_link/models/procurement_rule.py
odoo/addons/stock_orderpoint_purchase_link/models/purchase_order_line.py
odoo/addons/stock_orderpoint_purchase_link/models/stock_warehouse_orderpoint.py
odoo/addons/stock_orderpoint_purchase_link/static/description/icon.png
odoo/addons/stock_orderpoint_purchase_link/tests/__init__.py
odoo/addons/stock_orderpoint_purchase_link/tests/test_stock_orderpoint_purchase_link.py
odoo/addons/stock_orderpoint_purchase_link/views/purchase_order_views.xml
odoo11_addon_stock_orderpoint_purchase_link-11.0.1.1.0.dist-info/METADATA
odoo11_addon_stock_orderpoint_purchase_link-11.0.1.1.0.dist-info/WHEEL
odoo11_addon_stock_orderpoint_purchase_link-11.0.1.1.0.dist-info/top_level.txt
odoo11_addon_stock_orderpoint_purchase_link-11.0.1.1.0.dist-info/RECORD
